setup.cfg
setup.py
ethereum_helpers/__init__.py
ethereum_helpers/address.py
ethereum_helpers/aes.py
ethereum_helpers/coding.py
ethereum_helpers/hashes.py
ethereum_helpers/keys.py
ethereum_helpers/messages.py
ethereum_helpers/recover.py
ethereum_helpers/restrictions.py
ethereum_helpers/types.py
ethereum_helpers.egg-info/PKG-INFO
ethereum_helpers.egg-info/SOURCES.txt
ethereum_helpers.egg-info/dependency_links.txt
ethereum_helpers.egg-info/requires.txt
ethereum_helpers.egg-info/top_level.txt
ethereum_helpers/coordinates/__init__.py
ethereum_helpers/coordinates/affine.py
ethereum_helpers/coordinates/jacobian.py
ethereum_helpers/coordinates/utils.py
tests/__init__.py
tests/conftest.py
tests/test_messages.py
tests/test_recover.py
tests/utils.py
tests/fixtures/__init__.py
tests/fixtures/coding.py
tests/fixtures/keys.py
tests/fixtures/messages.py
tests/strategies/__init__.py
tests/strategies/messages.py