Metadata-Version: 1.1
Name: ethereum-helpers
Version: 0.0.5
Summary: Helper functions for working with ethereum network.
Home-page: https://github.com/lycantropos/ethereum_helpers
Author: Azat Ibrakov
Author-email: azatibrakov@gmail.com
License: UNKNOWN
Download-URL: https://github.com/lycantropos/ethereum_helpers/archive/master.tar.gz
Keywords: ethereum
Platform: UNKNOWN
